.gitignore
README.md
pyproject.toml
setup.cfg
setup.py
vitals.yaml
dist/idpaml-1.0.1.tar.gz
dist/idpaml-1.0.2.tar.gz
examples/v1/compute/initialization.ipynb
examples/v1/compute/mlflow-tracking.py
examples/v1/compute/src/train.py
examples/v2/azuremldataasset_test.ipynb
examples/v2/azuremljob_test.ipynb
examples/v2/.ipynb_aml_checkpoints/data_asset_test-checkpoint2023-0-31-20-35-30Z.ipynb
src/README.md
src/__init__.py
src/idpaml/__init__.py
src/idpaml/_initialization.py
src/idpaml/classification.py
src/idpaml/data.py
src/idpaml/job.py
src/idpaml/test_models.py
src/idpaml/testsdkv2.py
src/idpaml.egg-info/.amlignore
src/idpaml.egg-info/.amlignore.amltmp
src/idpaml.egg-info/PKG-INFO
src/idpaml.egg-info/SOURCES.txt
src/idpaml.egg-info/dependency_links.txt
src/idpaml.egg-info/requires.txt
src/idpaml.egg-info/top_level.txt